tensorizer/_NumpyTensor.py
tensorizer/__init__.py
tensorizer/_crypt_info.py
tensorizer/_internal_utils.py
tensorizer/_linear_partition.py
tensorizer/_syscalls.py
tensorizer/_tensor_path.py
tensorizer/_version.py
tensorizer/_wide_pipes.py
tensorizer/protobuf.py
tensorizer/serialization.py
tensorizer/stream_io.py
tensorizer/tensors.proto
tensorizer/tensors_pb2.py
tensorizer/torch_compat.py
tensorizer/utils.py
tensorizer/_crypt/__init__.py
tensorizer/_crypt/_cgroup_cpu_count.py
tensorizer/_crypt/_encryption.py
tensorizer/_crypt/_exceptions.py
tensorizer-2.12.0.dist-info/LICENSE
tensorizer-2.12.0.dist-info/METADATA
tensorizer-2.12.0.dist-info/WHEEL
tensorizer-2.12.0.dist-info/top_level.txt
tensorizer-2.12.0.dist-info/RECORD
