Metadata-Version: 2.1
Name: tensorizer
Version: 2.12.0
Summary: A tool for fast PyTorch module, model, and tensor serialization + deserialization.
Author: CoreWeave
License: MIT License
Project-URL: Homepage, https://github.com/coreweave/tensorizer
Project-URL: Repository, https://github.com/coreweave/tensorizer
Project-URL: Changelog, https://github.com/coreweave/tensorizer/blob/main/CHANGELOG.md
Keywords: tensorizer,machine learning,serialization,tensor,pytorch
Classifier: Programming Language :: Python :: 3
Classifier: License :: OSI Approved :: MIT License
Classifier: Development Status :: 5 - Production/Stable
Classifier: Operating System :: OS Independent
Classifier: Topic :: Scientific/Engineering :: Artificial Intelligence
Classifier: Topic :: System :: Distributed Computing
Classifier: Topic :: Internet
Classifier: Intended Audience :: Developers
Requires-Python: >=3.8
License-File: LICENSE
Requires-Dist: torch >=1.9.0
Requires-Dist: numpy >=1.19.5
Requires-Dist: protobuf >=3.19.5
Requires-Dist: psutil >=5.9.4
Requires-Dist: boto3 >=1.26.0
Requires-Dist: redis >=4.5.5
Requires-Dist: hiredis >=2.2.0
Requires-Dist: libnacl >=2.1.0
